prikarsartamContents/__init__.py
prikarsartamContents/content_generation.py
prikarsartamContents/model_load.py
prikarsartamGeneratesContents-2.1.dist-info/LICENSE
prikarsartamGeneratesContents-2.1.dist-info/METADATA
prikarsartamGeneratesContents-2.1.dist-info/WHEEL
prikarsartamGeneratesContents-2.1.dist-info/top_level.txt
prikarsartamGeneratesContents-2.1.dist-info/RECORD
